plover_split_at_apostrophe/__init__.py
plover_split_at_apostrophe-0.0.5.dist-info/METADATA
plover_split_at_apostrophe-0.0.5.dist-info/WHEEL
plover_split_at_apostrophe-0.0.5.dist-info/entry_points.txt
plover_split_at_apostrophe-0.0.5.dist-info/top_level.txt
plover_split_at_apostrophe-0.0.5.dist-info/zip-safe
plover_split_at_apostrophe-0.0.5.dist-info/RECORD
