Metadata-Version: 2.1
Name: plover-split-at-apostrophe
Version: 0.0.5
Summary: =?utf-8?q?Companion_plugin_for_B=C3=A9poSt=C3=A9no_-_split_words_at_apostrophekeys_and_punctuations=2E?=
Home-page: https://github.com/AntoineBalaine/plover-split-at-apostrophe
Author: AntoineBalaine
License: MIT
Keywords: =?utf-8?q?plover=5Fplugin_plover_b=C3=A9po_steno?=
Requires-Dist: plover (>=4.0.0.dev6)
